osl_ephys/__init__.py
osl_ephys/glm/README.md
osl_ephys/glm/__init__.py
osl_ephys/glm/glm_base.py
osl_ephys/glm/glm_epochs.py
osl_ephys/glm/glm_spectrum.py
osl_ephys/maxfilter/README.md
osl_ephys/maxfilter/__init__.py
osl_ephys/maxfilter/maxfilter.py
osl_ephys/preprocessing/README.md
osl_ephys/preprocessing/__init__.py
osl_ephys/preprocessing/batch.py
osl_ephys/preprocessing/ica_label.py
osl_ephys/preprocessing/mne_wrappers.py
osl_ephys/preprocessing/osl_wrappers.py
osl_ephys/preprocessing/plot_ica.py
osl_ephys/report/README.md
osl_ephys/report/__init__.py
osl_ephys/report/preproc_report.py
osl_ephys/report/src_report.py
osl_ephys/report/templates/raw_subject_panel.html
osl_ephys/report/templates/raw_summary_panel.html
osl_ephys/report/templates/src_subject_panel.html
osl_ephys/report/templates/src_summary_panel.html
osl_ephys/report/templates/subject_report.html
osl_ephys/report/templates/summary_report.html
osl_ephys/source_recon/README.md
osl_ephys/source_recon/__init__.py
osl_ephys/source_recon/batch.py
osl_ephys/source_recon/beamforming.py
osl_ephys/source_recon/freesurfer_utils.py
osl_ephys/source_recon/minimum_norm.py
osl_ephys/source_recon/nii.py
osl_ephys/source_recon/parcellation.py
osl_ephys/source_recon/sign_flipping.py
osl_ephys/source_recon/wrappers.py
osl_ephys/source_recon/files/Glasser50_space-MNI152NLin6_res-8x8x8.nii.gz
osl_ephys/source_recon/files/Glasser52_binary_space-MNI152NLin6_res-8x8x8.nii.gz
osl_ephys/source_recon/files/HarvOxf-sub-Schaefer100-combined-2mm.nii.gz
osl_ephys/source_recon/files/HarvOxf-sub-Schaefer100-combined-2mm_4d.nii.gz
osl_ephys/source_recon/files/HarvOxf-sub-Schaefer100-combined-2mm_4d_ds8.nii.gz
osl_ephys/source_recon/files/HarvardOxford-sub-prob-bin-2mm.nii.gz
osl_ephys/source_recon/files/MNI152_T1_2mm_brain.nii.gz
osl_ephys/source_recon/files/MNI152_T1_8mm_brain.nii.gz
osl_ephys/source_recon/files/Schaefer2018_100Parcels_7Networks_order_FSLMNI152_2mm.nii.gz
osl_ephys-2.4.0.dist-info/licenses/LICENSE
osl_ephys-2.4.0.dist-info/METADATA
osl_ephys-2.4.0.dist-info/WHEEL
osl_ephys-2.4.0.dist-info/entry_points.txt
osl_ephys-2.4.0.dist-info/top_level.txt
osl_ephys-2.4.0.dist-info/RECORD
