Metadata-Version: 2.4
Name: osl-ephys
Version: 2.4.0
Summary: OHBA Software Library for the analysis of electrophysiological data
Author: OHBA Analysis Group
License: MIT
Classifier: Development Status :: 4 - Beta
Classifier: Intended Audience :: Science/Research
Classifier: Topic :: Scientific/Engineering :: Bio-Informatics
Classifier: Topic :: Scientific/Engineering :: Information Analysis
Classifier: Topic :: Scientific/Engineering :: Mathematics
Classifier: Programming Language :: Python :: 3
Classifier: Programming Language :: Python :: 3.7
Classifier: Programming Language :: Python :: 3.8
Classifier: Programming Language :: Python :: 3.9
Classifier: Programming Language :: Python :: 3.10
Classifier: Programming Language :: Python :: 3.11
Classifier: Programming Language :: Python :: 3.12
Requires-Python: >=3.7
License-File: LICENSE
Requires-Dist: numpy
Requires-Dist: scipy
Requires-Dist: matplotlib
Requires-Dist: mne
Requires-Dist: scikit-learn
Requires-Dist: fslpy
Requires-Dist: sails
Requires-Dist: tabulate
Requires-Dist: pyyaml
Requires-Dist: neurokit2
Requires-Dist: jinja2
Requires-Dist: glmtools
Requires-Dist: numba
Requires-Dist: nilearn
Requires-Dist: dask
Requires-Dist: distributed
Requires-Dist: parse
Requires-Dist: opencv-python
Requires-Dist: panel
Requires-Dist: h5io
Provides-Extra: dev
Requires-Dist: setuptools; extra == "dev"
Requires-Dist: pytest; extra == "dev"
Requires-Dist: pytest-cov; extra == "dev"
Requires-Dist: coverage; extra == "dev"
Requires-Dist: flake8; extra == "dev"
Provides-Extra: doc
Requires-Dist: sphinx; extra == "doc"
Requires-Dist: numpydoc; extra == "doc"
Requires-Dist: sphinx_gallery; extra == "doc"
Requires-Dist: pydata-sphinx-theme; extra == "doc"
Provides-Extra: full
Requires-Dist: setuptools; extra == "full"
Requires-Dist: pytest; extra == "full"
Requires-Dist: pytest-cov; extra == "full"
Requires-Dist: coverage; extra == "full"
Requires-Dist: flake8; extra == "full"
Requires-Dist: sphinx; extra == "full"
Requires-Dist: numpydoc; extra == "full"
Requires-Dist: sphinx_gallery; extra == "full"
Requires-Dist: pydata-sphinx-theme; extra == "full"
Dynamic: author
Dynamic: classifier
Dynamic: description
Dynamic: description-content-type
Dynamic: license
Dynamic: license-file
Dynamic: provides-extra
Dynamic: requires-dist
Dynamic: requires-python
Dynamic: summary
